odoo/addons/stock_warehouse_security/README.rst
odoo/addons/stock_warehouse_security/__init__.py
odoo/addons/stock_warehouse_security/__manifest__.py
odoo/addons/stock_warehouse_security/i18n/fr.po
odoo/addons/stock_warehouse_security/i18n/it.po
odoo/addons/stock_warehouse_security/i18n/stock_multi_warehouse_security.pot
odoo/addons/stock_warehouse_security/i18n/stock_warehouse_security.pot
odoo/addons/stock_warehouse_security/models/__init__.py
odoo/addons/stock_warehouse_security/models/product.py
odoo/addons/stock_warehouse_security/models/res_users.py
odoo/addons/stock_warehouse_security/readme/CONTRIBUTORS.md
odoo/addons/stock_warehouse_security/readme/DESCRIPTION.md
odoo/addons/stock_warehouse_security/readme/ROADMAP.md
odoo/addons/stock_warehouse_security/readme/USAGE.md
odoo/addons/stock_warehouse_security/security/stock_security.xml
odoo/addons/stock_warehouse_security/static/description/icon.png
odoo/addons/stock_warehouse_security/static/description/index.html
odoo/addons/stock_warehouse_security/tests/__init__.py
odoo/addons/stock_warehouse_security/tests/common.py
odoo/addons/stock_warehouse_security/tests/test_stock_warehouse.py
odoo/addons/stock_warehouse_security/tests/test_stock_warehouse_security_rules.py
odoo/addons/stock_warehouse_security/views/res_users.xml
odoo_addon_stock_warehouse_security-18.0.1.0.0.4.dist-info/METADATA
odoo_addon_stock_warehouse_security-18.0.1.0.0.4.dist-info/WHEEL
odoo_addon_stock_warehouse_security-18.0.1.0.0.4.dist-info/top_level.txt
odoo_addon_stock_warehouse_security-18.0.1.0.0.4.dist-info/RECORD
