Metadata-Version: 2.1
Name: odoo-addon-stock_warehouse_security
Version: 18.0.1.0.0.4
Requires-Python: >=3.10
Requires-Dist: odoo==18.0.*
Summary: Restrict user access in multi-warehouse environment
Home-page: https://github.com/OCA/stock-logistics-warehouse
License: AGPL-3
Author: Akretion, Pierre Verkest, Odoo Community Association (OCA)
Author-email: support@odoo-community.org
Classifier: Programming Language :: Python
Classifier: Framework :: Odoo
Classifier: Framework :: Odoo :: 18.0
Classifier: License :: OSI Approved :: GNU Affero General Public License v3
Classifier: Development Status :: 3 - Alpha
